notifications/__init__.py
notifications/admin.py
notifications/delete_last_week_of_bills.py
notifications/models.py
notifications/tasks.py
notifications/tests.py
notifications/urls.py
notifications/utils.py
notifications/views.py
notifications/management/commands/send_notifications.py
notifications/migrations/0001_initial.py
notifications/migrations/0002_auto_20160527_1624.py
notifications/migrations/0003_auto_20160914_1101.py
notifications/migrations/0004_subscriptionprofile.py
notifications/migrations/0005_auto_20161121_1208.py
notifications/migrations/__init__.py
notifications/templates/notifications_email.html
notifications/templates/notifications_email.txt
notifications/templates/notifications_login.html
notifications/templates/notifications_signup.html
notifications/templates/password_change_done.html
notifications/templates/password_change_form.html
notifications/templates/signup_email.html
notifications/templates/signup_email.txt
notifications/templates/subscriptions_manage.html
notifications/templates/password_reset/recovery_done.html
notifications/templates/password_reset/recovery_email.txt
notifications/templates/password_reset/recovery_email_subject.txt
notifications/templates/password_reset/recovery_form.html
notifications/templates/password_reset/reset.html
notifications/templates/password_reset/reset_sent.html
notifications/templatetags/notifications_extras.py
django_councilmatic_notifications-0.1.27.dist-info/LICENSE
django_councilmatic_notifications-0.1.27.dist-info/METADATA
django_councilmatic_notifications-0.1.27.dist-info/WHEEL
django_councilmatic_notifications-0.1.27.dist-info/top_level.txt
django_councilmatic_notifications-0.1.27.dist-info/RECORD
