Metadata-Version: 2.1
Name: django-councilmatic-notifications
Version: 0.1.27
Summary: Core functions for councilmatic.org family
Home-page: http://councilmatic.org/
Author: DataMade, LLC
Author-email: info@datamade.us
License: MIT License
Platform: UNKNOWN
Classifier: Environment :: Web Environment
Classifier: Framework :: Django
Classifier: Intended Audience :: Developers
Classifier: License :: OSI Approved :: BSD License
Classifier: Operating System :: OS Independent
Classifier: Programming Language :: Python
Classifier: Programming Language :: Python :: 3.4
Classifier: Topic :: Internet :: WWW/HTTP
Classifier: Topic :: Internet :: WWW/HTTP :: Dynamic Content
Requires-Dist: django-councilmatic (<=0.8.7,>=0.7)
Requires-Dist: rq (<1.0,>=0.5.5)
Requires-Dist: django-rq (==0.9.3)
